analyzer/__init__.py
analyzer/snapshot_recorder.py
analyzer/snapshot_visualizer.py
analyzer/reporting/__init__.py
analyzer/reporting/analyzer.py
analyzer/reporting/cli.py
analyzer/reporting/math_utils.py
analyzer/reporting/snapshot_parser.py
propflow/__init__.py
propflow/_version.py
propflow/cli.py
propflow/simulator.py
propflow/webapp.py
propflow/bp/__init__.py
propflow/bp/computators.py
propflow/bp/engine_base.py
propflow/bp/engine_components.py
propflow/bp/engines.py
propflow/bp/factor_graph.py
propflow/computators/__init__.py
propflow/configs/__init__.py
propflow/configs/global_config_mapping.py
propflow/configs/loggers.py
propflow/core/__init__.py
propflow/core/agents.py
propflow/core/components.py
propflow/core/dcop_base.py
propflow/core/protocols.py
propflow/engines/__init__.py
propflow/nn/__init__.py
propflow/nn/torch_computators.py
propflow/nn/trainable_bp.py
propflow/policies/__init__.py
propflow/policies/bp_policies.py
propflow/policies/convergance.py
propflow/policies/cost_reduction.py
propflow/policies/damping.py
propflow/policies/message_pruning.py
propflow/policies/normalize_cost.py
propflow/policies/splitting.py
propflow/search/__init__.py
propflow/search/demo_search.py
propflow/search/search_agents.py
propflow/search/search_computator.py
propflow/search/search_engine.py
propflow/snapshots/__init__.py
propflow/snapshots/builder.py
propflow/snapshots/manager.py
propflow/snapshots/types.py
propflow/snapshots/utils.py
propflow/utils/__init__.py
propflow/utils/examples.py
propflow/utils/experiments.py
propflow/utils/fg_utils.py
propflow/utils/general_utils.py
propflow/utils/inbox_utils.py
propflow/utils/path_utils.py
propflow/utils/randomes.py
propflow/utils/save.py
propflow/utils/create/__init__.py
propflow/utils/create/create_cost_tables.py
propflow/utils/create/create_factor_graph_config.py
propflow/utils/create/create_factor_graphs_from_config.py
propflow/utils/tools/__init__.py
propflow/utils/tools/bct.py
propflow/utils/tools/convex_hull.py
propflow-0.1.3.dist-info/licenses/LICENSE
propflow-0.1.3.dist-info/METADATA
propflow-0.1.3.dist-info/WHEEL
propflow-0.1.3.dist-info/entry_points.txt
propflow-0.1.3.dist-info/top_level.txt
propflow-0.1.3.dist-info/RECORD
