Metadata-Version: 2.4
Name: propflow
Version: 0.1.3
Summary: Highly configurable belief propagation simulator for factor graphs
Author: Or Muller
License-Expression: MIT
Project-URL: Homepage, https://github.com/OrMullerHahitti/Belief-Propagation-Simulator
Project-URL: Repository, https://github.com/OrMullerHahitti/Belief-Propagation-Simulator
Project-URL: Issues, https://github.com/OrMullerHahitti/Belief-Propagation-Simulator/issues
Project-URL: Documentation, https://ormullerhahitti.github.io/Belief-Propagation-Simulator/index.html
Keywords: belief-propagation,factor-graphs,graphical-models,inference,optimization
Classifier: Development Status :: 3 - Alpha
Classifier: Intended Audience :: Science/Research
Classifier: Programming Language :: Python :: 3
Classifier: Programming Language :: Python :: 3 :: Only
Classifier: Programming Language :: Python :: 3.10
Classifier: Programming Language :: Python :: 3.11
Classifier: Programming Language :: Python :: 3.12
Classifier: Programming Language :: Python :: 3.13
Classifier: Operating System :: OS Independent
Classifier: Topic :: Scientific/Engineering :: Artificial Intelligence
Classifier: Topic :: Scientific/Engineering :: Mathematics
Classifier: Framework :: Matplotlib
Requires-Python: >=3.10
License-File: LICENSE
Requires-Dist: networkx~=3.4.2
Requires-Dist: numpy~=2.2.1
Requires-Dist: matplotlib~=3.10.0
Requires-Dist: scipy~=1.15.2
Requires-Dist: dash~=2.18.2
Requires-Dist: dash_cytoscape~=1.0.2
Requires-Dist: colorlog~=6.9.0
Requires-Dist: pandas~=2.2.3
Requires-Dist: seaborn~=0.13.2
Requires-Dist: psutil~=7.0.0
Requires-Dist: twine>=6.2.0
Requires-Dist: sphinx>=8.1.3
Requires-Dist: torch>=2.8.0
Requires-Dist: flake8>=7.3.0
Requires-Dist: gunicorn>=23.0.0
Provides-Extra: dev
Requires-Dist: pytest; extra == "dev"
Requires-Dist: pytest-cov; extra == "dev"
Requires-Dist: mypy; extra == "dev"
Requires-Dist: black; extra == "dev"
Requires-Dist: pylint; extra == "dev"
Requires-Dist: jupyter; extra == "dev"
Requires-Dist: build; extra == "dev"
Requires-Dist: twine; extra == "dev"
Requires-Dist: pre-commit; extra == "dev"
Provides-Extra: torch
Requires-Dist: torch>=2.2; extra == "torch"
Dynamic: license-file
